elasticsearch_ltr/__init__.py
elasticsearch_ltr/ltr.py
tests/__init__.py
tests/conftest.py
tests/test_ltr.py
elasticsearch_ltr-1.0.2.dist-info/LICENSE
elasticsearch_ltr-1.0.2.dist-info/METADATA
elasticsearch_ltr-1.0.2.dist-info/WHEEL
elasticsearch_ltr-1.0.2.dist-info/top_level.txt
elasticsearch_ltr-1.0.2.dist-info/RECORD
