Metadata-Version: 2.1
Name: elasticsearch-ltr
Version: 1.0.2
Summary: Python interface for Elasticsearch LTR extension
Home-page: https://github.com/Saluev/elasticsearch-ltr-py
Author: Tigran Saluev
Author-email: tigran@saluev.com
License: UNKNOWN
Platform: UNKNOWN
Classifier: Programming Language :: Python :: 3
Classifier: License :: OSI Approved :: MIT License
Classifier: Operating System :: OS Independent
Requires-Python: >=3.6
Requires-Dist: elasticsearch (<8.0.0,>=7.0.0)
